dagster_cloudquery/__init__.py
dagster_cloudquery/py.typed
dagster_cloudquery/resource.py
dagster_cloudquery/version.py
dagster_cloudquery-0.1.2.dist-info/LICENSE
dagster_cloudquery-0.1.2.dist-info/METADATA
dagster_cloudquery-0.1.2.dist-info/WHEEL
dagster_cloudquery-0.1.2.dist-info/top_level.txt
dagster_cloudquery-0.1.2.dist-info/RECORD
